{"id": "chaordic", "name": "Chaordic", "category": "advertising", "website_url": "https://www.chaordic.com.br/", "ghostery_id": "1254", "company_id": null, "iab_vendor": null, "truste_type": null, "description": null, "privacy_url": null, "domains": ["chaordicsystems.com"], "overview": {"bad_qs": 0.0, "beacon": 0.0, "content_length": 39235.64406626159, "cookies": 0.4698331933672546, "font": 0.10680235143012401, "has_blocking": 0.7281282418613841, "hosts": 1.0, "https": 1.5079780664921207, "iframe": 0.4693556620395528, "image": 0.1425266347214675, "media": 0.0, "plugin": 0.0, "reach": 0.0002924576313871411, "reach_rank": 860, "referer_leaked": 0.5770307431375455, "referer_leaked_header": 0.5627048033064928, "referer_leaked_url": 0.35168535625483704, "requests": 6.342768693704821, "requests_failed": 2.7191539462200924, "requests_tracking": 2.3434849906963726, "script": 0.9979252087141234, "site_reach": 0.0001898787977139476, "site_reach_rank": 839, "stylesheet": 0.0001070328837952214, "tracked": 0.4698331933672546, "xhr": 0.4660952757331753}, "date_range": ["2018-11", "2018-11"]}