{"id": "findizer.fr", "name": "Findizer", "category": "misc", "website_url": "http://www.findizer.fr/", "ghostery_id": "findizer.fr", "company_id": null, "iab_vendor": null, "truste_type": null, "description": null, "privacy_url": null, "domains": ["findizer.fr"], "overview": {"bad_qs": 0.0, "beacon": 0.0, "content_length": 45.1939393939394, "cookies": 0.8848484848484849, "font": 0.0, "has_blocking": 0.20606060606060608, "hosts": 1.0, "https": 0.9393939393939394, "iframe": 0.0, "image": 0.2606060606060606, "media": 0.0, "plugin": 0.0, "reach": 3.973020235709322e-07, "reach_rank": 1105, "referer_leaked": 0.509090909090909, "referer_leaked_header": 0.4363636363636363, "referer_leaked_url": 0.496969696969697, "requests": 2.878787878787879, "requests_failed": 0.8060606060606059, "requests_tracking": 1.975757575757576, "script": 0.7575757575757576, "site_reach": 3.3118394950107137e-06, "site_reach_rank": 1101, "stylesheet": 0.0, "tracked": 0.8848484848484849, "xhr": 0.048484848484848485}, "date_range": ["2017-05", "2018-11"]}