{"id": "intercom", "name": "Intercom", "category": "customer_interaction", "website_url": "http://intercom.io/", "ghostery_id": "792", "company_id": "intercom", "iab_vendor": null, "truste_type": null, "description": null, "privacy_url": "https://docs.intercom.com/pricing-privacy-and-terms/intercom-inc-privacy-policy", "domains": ["intercom.io", "intercomassets.com", "intercomcdn.com"], "overview": {"bad_qs": 0.001350857857248606, "beacon": 0.022368442697109768, "content_length": 376504.8536460989, "cookies": 0.04513760260564886, "font": 0.1775019328519024, "has_blocking": 0.5304745768288069, "hosts": 1.8450500896514288, "https": 1.629970883847938, "iframe": 0.0004888881577865145, "image": 0.1941780855718774, "media": 0.01763418927143821, "plugin": 0.0, "reach": 0.003659452623469778, "reach_rank": 186, "referer_leaked": 0.5605638992614038, "referer_leaked_header": 0.5604816502442795, "referer_leaked_url": 0.00014673224654965374, "requests": 30.198834695925388, "requests_failed": 25.052418943593626, "requests_tracking": 0.5826816469543189, "script": 0.977761181753878, "site_reach": 0.007858995121660424, "site_reach_rank": 100, "stylesheet": 0.011701074172163643, "tracked": 0.046079189353687225, "xhr": 0.5693698080307941}, "date_range": ["2017-05", "2018-11"]}