{"id": "myfonts_counter", "name": "MyFonts", "category": "site_analytics", "website_url": "http://www.myfonts.com/", "ghostery_id": "1634", "company_id": "myfonts", "iab_vendor": null, "truste_type": null, "description": null, "privacy_url": "https://www.myfonts.com/info/legal/#Privacy", "domains": ["myfonts.net"], "overview": {"bad_qs": 0.0, "beacon": 0.0, "content_length": 625.4199915795892, "cookies": 0.0269589250910094, "font": 0.0003112285451925625, "has_blocking": 0.031130113494071236, "hosts": 1.0, "https": 0.9509529219188374, "iframe": 0.0, "image": 0.0020742520533825006, "media": 0.0, "plugin": 0.0, "reach": 0.002653698202091801, "reach_rank": 244, "referer_leaked": 0.5126170056002991, "referer_leaked_header": 0.5126170056002991, "referer_leaked_url": 0.0, "requests": 1.6461766979649464, "requests_failed": 0.5130380261395683, "requests_tracking": 0.10082716018016777, "script": 0.10825218404404746, "site_reach": 0.007276111370538537, "site_reach_rank": 108, "stylesheet": 0.8916235060122459, "tracked": 0.0269589250910094, "xhr": 0.0009110013392808533}, "date_range": ["2017-05", "2018-11"]}