{"id": "next_performance", "name": "Next Performance", "category": "advertising", "website_url": "http://www.nextperformance.com/", "ghostery_id": "706", "company_id": "nextperf", "iab_vendor": null, "truste_type": null, "description": null, "privacy_url": "http://www.nextperf.com/privacy/", "domains": ["nxtck.com"], "overview": {"bad_qs": 0.0005368132013667547, "beacon": 0.0, "content_length": 312.239358649491, "cookies": 0.19164584455372988, "font": 0.0, "has_blocking": 0.7061724688992681, "hosts": 1.0, "https": 0.9936606598917544, "iframe": 0.031668447214840065, "image": 0.3458154174870432, "media": 0.0, "plugin": 0.0, "reach": 0.001363600742171738, "reach_rank": 419, "referer_leaked": 0.13213727584958634, "referer_leaked_header": 0.1303449554568651, "referer_leaked_url": 0.018018558903770937, "requests": 1.727514325319395, "requests_failed": 1.3257114099292784, "requests_tracking": 0.3983401170747212, "script": 0.6338192316861055, "site_reach": 0.001435130447837976, "site_reach_rank": 360, "stylesheet": 1.0594997395396472e-05, "tracked": 0.1919866503032818, "xhr": 0.0004644140524982121}, "date_range": ["2017-05", "2018-11"]}