{"id": "pushcrew", "name": "Pushcrew", "category": "customer_interaction", "website_url": null, "ghostery_id": "2572", "company_id": "pushcrew", "iab_vendor": null, "truste_type": null, "description": null, "privacy_url": "https://pushcrew.com/privacy-policy/", "domains": ["pushcrew.com"], "overview": {"bad_qs": 0.0, "beacon": 0.0, "content_length": 5564.774534409544, "cookies": 0.6655003242554033, "font": 0.0, "has_blocking": 0.2463571645788527, "hosts": 1.0, "https": 1.5454159079334489, "iframe": 0.0, "image": 0.4610179054932896, "media": 0.0, "plugin": 0.0, "reach": 0.0006571929284805166, "reach_rank": 655, "referer_leaked": 0.7063271938534366, "referer_leaked_header": 0.7062355962818714, "referer_leaked_url": 0.003869081422913316, "requests": 3.2512777861233344, "requests_failed": 1.183422305107847, "requests_tracking": 1.962734443984421, "script": 0.9984941359234684, "site_reach": 0.0015996184760901748, "site_reach_rank": 331, "stylesheet": 0.5409642659553809, "tracked": 0.6655003242554033, "xhr": 0.005437231848109243}, "date_range": ["2018-03", "2018-11"]}